__init__.py
main.py
python_castlight_common-1.0.3.dist-info/METADATA
python_castlight_common-1.0.3.dist-info/WHEEL
python_castlight_common-1.0.3.dist-info/licenses/LICENSE
python_castlight_common-1.0.3.dist-info/RECORD
