Metadata-Version: 2.1
Name: python-castlight-common
Version: 1.0.3
Summary: A python package
Project-URL: Homepage, https://github.com/
Project-URL: Bug Tracker, https://github.com/
Author: ed53
License-File: LICENSE
Classifier: License :: OSI Approved :: MIT License
Classifier: Operating System :: OS Independent
Classifier: Programming Language :: Python :: 3
Requires-Python: >=3.7
